vk_audio/__init__.py
vk_audio/decoder.py
vk_audio-6.5.dist-info/METADATA
vk_audio-6.5.dist-info/WHEEL
vk_audio-6.5.dist-info/top_level.txt
vk_audio-6.5.dist-info/RECORD
