Metadata-Version: 2.1
Name: vk-audio
Version: 6.5
Summary: audio vk Library
Home-page: https://vk.com/imartemy
Author: Ivan
Author-email: imartemy1524@gmail.com
License: MIT
Keywords: vk,audio,vkaudio,music,vkmusic
Platform: UNKNOWN
Classifier: Development Status :: 3 - Alpha
Classifier: Intended Audience :: Developers
Classifier: Topic :: Software Development :: Build Tools
Classifier: License :: OSI Approved :: MIT License
Classifier: Programming Language :: Python :: 3
Classifier: Programming Language :: Python :: 3.4
Classifier: Programming Language :: Python :: 3.5
Classifier: Programming Language :: Python :: 3.6
Classifier: Programming Language :: Python :: 3.7
Classifier: Programming Language :: Python :: 3.8
Requires-Python: >=3.4
Requires-Dist: vk-api
Requires-Dist: datetime
